[
    {
        "id": "60627e22237dc214",
        "type": "tab",
        "label": "Flow 2",
        "disabled": false,
        "info": "",
        "env": []
    },
    {
        "id": "1b373876dab8a947",
        "type": "comment",
        "z": "60627e22237dc214",
        "name": "Relay Control Block",
        "info": "",
        "x": 210,
        "y": 160,
        "wires": []
    },
    {
        "id": "7f542e9619766dd8",
        "type": "debug",
        "z": "60627e22237dc214",
        "name": "Log JSON",
        "active": true,
        "tosidebar": true,
        "console": false,
        "tostatus": false,
        "complete": "payload",
        "targetType": "msg",
        "statusVal": "",
        "statusType": "auto",
        "x": 490,
        "y": 280,
        "wires": []
    },
    {
        "id": "837f99d92b99cae7",
        "type": "mqtt in",
        "z": "60627e22237dc214",
        "name": "Qubitro Downlink",
        "topic": "2487796d-7e00-4f94-81c1-4a6cb26044c6",
        "qos": "2",
        "datatype": "auto-detect",
        "broker": "87e6d049dc280d47",
        "nl": false,
        "rap": true,
        "rh": 0,
        "inputs": 0,
        "x": 200,
        "y": 220,
        "wires": [
            [
                "7f542e9619766dd8",
                "f74fa4937866cfb4"
            ]
        ]
    },
    {
        "id": "f74fa4937866cfb4",
        "type": "function",
        "z": "60627e22237dc214",
        "name": "JSON decode",
        "func": "if (msg.payload.CMID==\"5\")\n{\n    msg.payload=\"1\"\n}\nelse { msg.payload = \"0\"}\n\nreturn msg;",
        "outputs": 1,
        "timeout": "",
        "noerr": 0,
        "initialize": "",
        "finalize": "",
        "libs": [],
        "x": 500,
        "y": 220,
        "wires": [
            [
                "a2b7618da5dfe410",
                "b4e585c5226bc45f"
            ]
        ]
    },
    {
        "id": "a2b7618da5dfe410",
        "type": "serial out",
        "z": "60627e22237dc214",
        "name": "LED",
        "serial": "7635997c9e922fe5",
        "x": 770,
        "y": 220,
        "wires": []
    },
    {
        "id": "b4e585c5226bc45f",
        "type": "debug",
        "z": "60627e22237dc214",
        "name": "FunctionOut",
        "active": true,
        "tosidebar": true,
        "console": false,
        "tostatus": false,
        "complete": "payload",
        "targetType": "msg",
        "statusVal": "",
        "statusType": "auto",
        "x": 770,
        "y": 280,
        "wires": []
    },
    {
        "id": "87e6d049dc280d47",
        "type": "mqtt-broker",
        "name": "",
        "broker": "broker.qubitro.com:1883",
        "port": "1883",
        "clientid": "",
        "autoConnect": true,
        "usetls": false,
        "protocolVersion": "4",
        "keepalive": "60",
        "cleansession": true,
        "autoUnsubscribe": true,
        "birthTopic": "",
        "birthQos": "0",
        "birthRetain": "false",
        "birthPayload": "",
        "birthMsg": {},
        "closeTopic": "",
        "closeQos": "0",
        "closeRetain": "false",
        "closePayload": "",
        "closeMsg": {},
        "willTopic": "",
        "willQos": "0",
        "willRetain": "false",
        "willPayload": "",
        "willMsg": {},
        "userProps": "",
        "sessionExpiry": ""
    },
    {
        "id": "7635997c9e922fe5",
        "type": "serial-port",
        "serialport": "COM4",
        "serialbaud": "115200",
        "databits": "8",
        "parity": "none",
        "stopbits": "1",
        "waitfor": "",
        "dtr": "none",
        "rts": "none",
        "cts": "none",
        "dsr": "none",
        "newline": "\\n",
        "bin": "false",
        "out": "char",
        "addchar": "",
        "responsetimeout": "10000"
    }
]